README-public-pypi.md
cisco_radkit_common-1.9.2.dist-info/METADATA
cisco_radkit_common-1.9.2.dist-info/WHEEL
cisco_radkit_common-1.9.2.dist-info/entry_points.txt
cisco_radkit_common-1.9.2.dist-info/licenses/LICENSE.md
radkit_common/LICENSE.html
radkit_common/LICENSE.md
radkit_common/__init__.py
radkit_common/access/__init__.py
radkit_common/access/__init__.pyi
radkit_common/access/admin.py
radkit_common/access/admin.pyi
radkit_common/access/auth.py
radkit_common/access/auth.pyi
radkit_common/access/ca.py
radkit_common/access/ca.pyi
radkit_common/access/challenge.py
radkit_common/access/challenge.pyi
radkit_common/access/claims/__init__.py
radkit_common/access/claims/__init__.pyi
radkit_common/access/claims/_claims.py
radkit_common/access/claims/_claims.pyi
radkit_common/access/claims/base.py
radkit_common/access/claims/base.pyi
radkit_common/access/claims/granting/__init__.py
radkit_common/access/claims/granting/__init__.pyi
radkit_common/access/claims/granting/_claims.py
radkit_common/access/claims/granting/_claims.pyi
radkit_common/access/claims/granting/base.py
radkit_common/access/claims/granting/base.pyi
radkit_common/access/claims/granting/models.py
radkit_common/access/claims/granting/models.pyi
radkit_common/access/claims/granting/results.py
radkit_common/access/claims/granting/results.pyi
radkit_common/access/claims/models.py
radkit_common/access/claims/models.pyi
radkit_common/access/claims/standard_grants.py
radkit_common/access/claims/standard_grants.pyi
radkit_common/access/claims/types.py
radkit_common/access/claims/types.pyi
radkit_common/access/client/__init__.py
radkit_common/access/client/__init__.pyi
radkit_common/access/client/auth_flows.py
radkit_common/access/client/auth_flows.pyi
radkit_common/access/client/cert.py
radkit_common/access/client/cert.pyi
radkit_common/access/client/client.py
radkit_common/access/client/client.pyi
radkit_common/access/client/models.py
radkit_common/access/client/models.pyi
radkit_common/access/client/refresh_loop.py
radkit_common/access/client/refresh_loop.pyi
radkit_common/access/endpoints.py
radkit_common/access/endpoints.pyi
radkit_common/access/exceptions.py
radkit_common/access/exceptions.pyi
cisco_radkit_common-1.9.2.dist-info/RECORD
