Metadata-Version: 2.1
Name: cisco_radkit_common
Version: 1.9.2
Summary: Cisco RADKit Common Library
Keywords: cisco,remote,automation
Author-Email: "Cisco Systems Inc." <radkit@cisco.com>
License: Cisco Remote Automation Development Kit (RADKit) -- Copyright (c) 2018-2025 by Cisco Systems, Inc.
Classifier: Development Status :: 5 - Production/Stable
Classifier: Development Status :: 6 - Mature
Classifier: Intended Audience :: Developers
Classifier: Intended Audience :: Information Technology
Classifier: Intended Audience :: System Administrators
Classifier: Intended Audience :: Telecommunications Industry
Classifier: License :: Other/Proprietary License
Classifier: Operating System :: MacOS
Classifier: Operating System :: Microsoft :: Windows
Classifier: Operating System :: POSIX :: Linux
Classifier: Programming Language :: Python :: 3 :: Only
Classifier: Programming Language :: Python :: 3.10
Classifier: Programming Language :: Python :: 3.11
Classifier: Programming Language :: Python :: 3.12
Classifier: Programming Language :: Python :: 3.13
Classifier: Programming Language :: Python :: Implementation :: CPython
Classifier: Topic :: System :: Systems Administration
Project-URL: HomePage, https://radkit.cisco.com
Project-URL: Documentation, https://radkit.cisco.com/docs/index.html
Requires-Python: <3.14,>=3.10
Requires-Dist: typing-extensions<5.0,>=4.12.2
Requires-Dist: pydantic==2.11.7
Requires-Dist: email-validator>=2.0.0
Requires-Dist: pydantic-settings~=2.7.1
Requires-Dist: cryptography<45.0,>=43.0.1
Requires-Dist: pyte==0.8.2
Requires-Dist: anyio<4.9.0,>=4.8.0
Requires-Dist: exceptiongroup>=1.0.2
Requires-Dist: httpx>=0.26.0
Requires-Dist: aiohttp<4.0,>=3.9
Requires-Dist: prompt-toolkit<4.0,>=3.0.50
Requires-Dist: tomlkit<1.0,>=0.11.8
Requires-Dist: zstandard<1.0,>=0.19.0
Requires-Dist: asn1<3.0,>=2.5.0
Requires-Dist: pysnmp<7.1,>=6.1.4
Requires-Dist: pyasn1<1.0
Requires-Dist: starlette<1.0,>=0.25.0
Requires-Dist: pyjwt!=2.10.0,<3.0,>=2.9
Requires-Dist: wsproto<1.3.0,>=0.14.0
Provides-Extra: pac
Requires-Dist: pypac<1.0,>=0.17.2; extra == "pac"
